{
  "twitter": {
    "username": "dnshzel",
    "name": "keqing",
    "description": "life is really unpredictable",
    "followers": 45,
    "following": 86,
    "tweets": 569,
    "profile_image_url": "https://pbs.twimg.com/profile_images/1662121803098226688/evN-AwHX_400x400.jpg",
    "profile_image_path": "img/twitter_profile.jpg"
  },
  "instagram": {
    "username": "dnshzel",
    "name": "Danish Hakim",
    "media_count": 0,
    "biography": "achieving what others can\u2019t do\ninsyaAllah your future pentester\nsagacious 34\u2019 / luminuex 39\u2019",
    "followers": 588,
    "following": 678,
    "profile_image_url": "https://scontent-ord5-2.cdninstagram.com/v/t51.2885-19/274086862_1113777356121305_1193622962455057962_n.jpg?stp=dst-jpg_s206x206_tt6&_nc_cat=103&ccb=7-5&_nc_sid=bf7eb4&efg=eyJ2ZW5jb2RlX3RhZyI6InByb2ZpbGVfcGljLnd3dy4xMDgwLkMzIn0%3D&_nc_ohc=LQOaKqmwTUIQ7kNvwGjqZbr&_nc_oc=AdrwjxcJ8Ya9EPwlcAMHzNB28jcqsGX-h-2nPFbTEUG9p-T6yluEyA52_kzhE0JnQ60&_nc_zt=24&_nc_ht=scontent-ord5-2.cdninstagram.com&edm=AP4hL3IEAAAA&_nc_tpa=Q5bMBQGGqu-c-FpW7q4wmqF6GCTSj7GyEBqJUzdgKhiU7C8fv1rewUsGosLST5CUrijT9PuHZjjBEV6S&oh=00_Af1jRUB9irs4dumgU9hzvaPVBMovzOOD75dLg8mWzDBNRw&oe=69E8B354",
    "profile_image_path": "img/insta_profile.jpg"
  }
}